{
  "project_info": {
    "project_number": "713558308519",
    "project_id": "safe-tech-arq",
    "storage_bucket": "safe-tech-arq.appspot.com"
  },
  "client": [
    {
      "client_info": {
        "mobilesdk_app_id": "1:713558308519:android:eb2697531740a930528d82",
        "android_client_info": {
          "package_name": "com.safetech.mobile_safetech"
        }
      },
      "oauth_client": [
        {
          "client_id": "713558308519-8muep8ipj6gb48d8mul0ep1th13p3kpi.apps.googleusercontent.com",
          "client_type": 1,
          "android_info": {
            "package_name": "com.safetech.mobile_safetech",
            "certificate_hash": "fc6a5d3c51ab37fd33ca979d949027a5fca641ee"
          }
        },
        {
          "client_id": "713558308519-vsui6p9a8f3jmfbg377s0mvn8tu85t9d.apps.googleusercontent.com",
          "client_type": 1,
          "android_info": {
            "package_name": "com.safetech.mobile_safetech",
            "certificate_hash": "d3859fbe7d7b3467c349293c8b4c799905c45a87"
          }
        },
        {
          "client_id": "713558308519-qunnn2cjpb7p8u29rtlev5r8u0dq2a2f.apps.googleusercontent.com",
          "client_type": 3
        }
      ],
      "api_key": [
        {
          "current_key": "AIzaSyBjkkVFuLtCwk77GpUmAJwMzRlqvAkrBns"
        }
      ],
      "services": {
        "appinvite_service": {
          "other_platform_oauth_client": [
            {
              "client_id": "713558308519-p9jmteheqa3tgasb7c2f8g924vukarro.apps.googleusercontent.com",
              "client_type": 3
            }
          ]
        }
      }
    }
  ],
  "configuration_version": "1"
}